{
	"$schema": "https://raw.githubusercontent.com/xen-42/outer-wilds-new-horizons/main/NewHorizons/Schemas/body_schema.json",
	"name": "Red exit",
	"starSystem": "O32.FunnySystem",
	"Base": {
		"surfaceGravity": 0,
		"surfaceSize": 0,
		"hasMapMarker": true
	},
	"Orbit": {
		"semiMajorAxis": 40000,
		"inclination": 0,
		"primaryBody": "RED IMPOSTOR SUS",
		"isMoon": false,
		"longitudeOfAscendingNode": 0,
		"axialTilt": 0,
		"argumentOfPeriapsis": 0,
		"eccentricity": 0,
		"isTidallyLocked": true,
		"dottedOrbitLine": true
	},
	"Props": {
		"reveal": [
			{
				"radius": 500,
				"revealOn": "enter",
				"reveals": [ "RED_LANDING", "RING_LANDING", "VIDA_LANDING", "BGYQQAOHOISTGIWBYAUYHM_LANDING", "DABABY_LANDING", "PISSHARTS_LANDING", "AAA_LANDING", "DESFILADEIRO_LANDING" ]
			}
		],
		"singularities": [
			{
				"type": "whiteHole",
				"size": 50,
				"pairedSingularity": "tp to Red"
			}
		]
	},
	"ShipLog": {
		"mapMode": {
			"remove": true
		}
	}
}